obsidian_tmdb_cover/__init__.py
obsidian_tmdb_cover/__main__.py
obsidian_tmdb_cover/cli.py
obsidian_tmdb_cover/fetcher.py
obsidian_tmdb_cover/updater.py
obsidian_tmdb_cover/utils.py
obsidian_tmdb_cover-0.1.3.dist-info/METADATA
obsidian_tmdb_cover-0.1.3.dist-info/WHEEL
obsidian_tmdb_cover-0.1.3.dist-info/entry_points.txt
obsidian_tmdb_cover-0.1.3.dist-info/RECORD
